{
  "uid": "types/nworder",
  "namePlural": "Orders",
  "workspace": {
    "uid": "workspaces/northwind",
    "name": "Northwind"
  },
  "processes": [],
  "versions": [
    {
      "date": "2015-11-11T00:03:37.048",
      "person": {
        "uid": "users/6eklbxgrsdan",
        "name": "Max Mustermann"
      },
      "changes": [],
      "action": "Added",
      "type": "_new"
    }
  ],
  "entities": [
    {
      "uid": "entities/order03",
      "name": "Order03"
    },
    {
      "uid": "entities/order27",
      "name": "Order27"
    },
    {
      "uid": "entities/order15",
      "name": "Order15"
    },
    {
      "uid": "entities/order31",
      "name": "Order31"
    },
    {
      "uid": "entities/order37",
      "name": "Order39"
    },
    {
      "uid": "entities/order10",
      "name": "Order10"
    },
    {
      "uid": "entities/order34",
      "name": "Order34"
    },
    {
      "uid": "entities/order22",
      "name": "Order22"
    },
    {
      "uid": "entities/order18",
      "name": "Order18"
    },
    {
      "uid": "entities/order06",
      "name": "Order06"
    },
    {
      "uid": "entities/order13",
      "name": "Order13"
    },
    {
      "uid": "entities/order01",
      "name": "Order01"
    },
    {
      "uid": "entities/order09",
      "name": "Order09"
    },
    {
      "uid": "entities/order16",
      "name": "Order16"
    },
    {
      "uid": "entities/order04",
      "name": "Order04"
    },
    {
      "uid": "entities/order32",
      "name": "Order32"
    },
    {
      "uid": "entities/order20",
      "name": "Order20"
    },
    {
      "uid": "entities/order28",
      "name": "Order28"
    },
    {
      "uid": "entities/order30",
      "name": "Order30"
    },
    {
      "uid": "entities/order14",
      "name": "Order14"
    },
    {
      "uid": "entities/order02",
      "name": "Order02"
    },
    {
      "uid": "entities/order26",
      "name": "Order26"
    },
    {
      "uid": "entities/order40",
      "name": "Order42"
    },
    {
      "uid": "entities/order39",
      "name": "Order41"
    },
    {
      "uid": "entities/order25",
      "name": "Order25"
    },
    {
      "uid": "entities/order05",
      "name": "Order05"
    },
    {
      "uid": "entities/order21",
      "name": "Order21"
    },
    {
      "uid": "entities/order33",
      "name": "Order33"
    },
    {
      "uid": "entities/order29",
      "name": "Order29"
    },
    {
      "uid": "entities/order17",
      "name": "Order17"
    },
    {
      "uid": "entities/order38",
      "name": "Order40"
    },
    {
      "uid": "entities/order36",
      "name": "Order36"
    },
    {
      "uid": "entities/order24",
      "name": "Order24"
    },
    {
      "uid": "entities/order12",
      "name": "Order12"
    },
    {
      "uid": "entities/order08",
      "name": "Order08"
    },
    {
      "uid": "entities/order35",
      "name": "Order35"
    },
    {
      "uid": "entities/order23",
      "name": "Order23"
    },
    {
      "uid": "entities/order11",
      "name": "Order11"
    },
    {
      "uid": "entities/order07",
      "name": "Order07"
    },
    {
      "uid": "entities/order19",
      "name": "Order19"
    }
  ],
  "name": "Order",
  "allowFreeAttributes": "true",
  "properties": [
    {
      "uid": "properties/nworderproduct",
      "name": "Product"
    },
    {
      "uid": "properties/nwordercustomer",
      "name": "Customer"
    },
    {
      "uid": "properties/nworderdiscount",
      "name": "Discount"
    },
    {
      "uid": "properties/nworderquantity",
      "name": "Quantity"
    },
    {
      "uid": "properties/nwordershippingdate",
      "name": "Shipping date"
    }
  ]
}